lamon/__init__.py
lamon/admin.py
lamon/forms.py
lamon/models.py
lamon/static/bootstrap/css/bootstrap-grid.css
lamon/static/bootstrap/css/bootstrap-grid.css.map
lamon/static/bootstrap/css/bootstrap-grid.min.css
lamon/static/bootstrap/css/bootstrap-grid.min.css.map
lamon/static/bootstrap/css/bootstrap-reboot.css
lamon/static/bootstrap/css/bootstrap-reboot.css.map
lamon/static/bootstrap/css/bootstrap-reboot.min.css
lamon/static/bootstrap/css/bootstrap-reboot.min.css.map
lamon/static/bootstrap/css/bootstrap.css
lamon/static/bootstrap/css/bootstrap.css.map
lamon/static/bootstrap/css/bootstrap.min.css
lamon/static/bootstrap/css/bootstrap.min.css.map
lamon/static/bootstrap/js/bootstrap.bundle.js
lamon/static/bootstrap/js/bootstrap.bundle.js.map
lamon/static/bootstrap/js/bootstrap.bundle.min.js
lamon/static/bootstrap/js/bootstrap.bundle.min.js.map
lamon/static/bootstrap/js/bootstrap.js
lamon/static/bootstrap/js/bootstrap.js.map
lamon/static/bootstrap/js/bootstrap.min.js
lamon/static/bootstrap/js/bootstrap.min.js.map
lamon/static/css/base.css
lamon/templates/base.html
lamon/templates/game/index.html
lamon/templates/game/stats.html
lamon/templates/game/stats_one.html
lamon/templates/macros.html
lamon/templates/main/index.html
lamon/templates/main/stats.html
lamon/templates/user/profile.html
lamon/templates/user/stats.html
lamon/templates/watcher/create.html
lamon/templates/watcher/edit.html
lamon/templates/watcher/index.html
lamon/templates/watcher/index_one.html
lamon/templates/watcher/stats.html
lamon/views/__init__.py
lamon/views/game.py
lamon/views/main.py
lamon/views/user.py
lamon/views/watcher.py
lamon/watcher/__init__.py
lamon/watcher/manager.py
lamon/watcher/plugin/__init__.py
lamon/watcher/plugin/quake3.py
lamon/watcher/plugin/source_engine.py
lamon-0.1.0.dist-info/WHEEL
lamon-0.1.0.dist-info/METADATA
lamon-0.1.0.dist-info/RECORD
