Metadata-Version: 2.1
Name: lamon
Version: 0.1.0
Summary: Monitor gameservers
Author: Fabian Geiselhart
Author-email: me@f4814n.de
Requires-Python: >=3.6,<4.0
Classifier: Programming Language :: Python :: 3
Classifier: Programming Language :: Python :: 3.6
Classifier: Programming Language :: Python :: 3.7
Requires-Dist: flask (>=1.0,<2.0)
Requires-Dist: flask-admin (>=1.5,<2.0)
Requires-Dist: flask-sqlalchemy (>=2.3,<3.0)
Requires-Dist: flask-user (==0.6.21)
Requires-Dist: flask-wtf (>=0.14.2,<0.15.0)
Requires-Dist: jinja2 (>=2.10,<3.0)
Requires-Dist: psycopg2 (>=2.8,<3.0)
Requires-Dist: python-valve (>=0.2.1,<0.3.0)
Requires-Dist: sqlalchemy (>=1.2,<2.0)
Requires-Dist: toml (>=0.10.0,<0.11.0)
